{
	"name": "pregunta 3",
	"events": [
		{
			"eventType": "block",
			"conditions": [
				{
					"id": "on-object-clicked",
					"objectClass": "Mouse",
					"sid": 242593844248944,
					"parameters": {
						"mouse-button": "left",
						"click-type": "clicked",
						"object-clicked": "A"
					}
				}
			],
			"actions": [
				{
					"id": "go-to-layout-by-name",
					"objectClass": "System",
					"sid": 853913031251656,
					"parameters": {
						"layout": "\"Falso\""
					}
				}
			],
			"sid": 629222224850320
		},
		{
			"eventType": "block",
			"conditions": [
				{
					"id": "on-object-clicked",
					"objectClass": "Mouse",
					"sid": 859219252354860,
					"parameters": {
						"mouse-button": "left",
						"click-type": "clicked",
						"object-clicked": "B"
					}
				}
			],
			"actions": [
				{
					"id": "go-to-layout-by-name",
					"objectClass": "System",
					"sid": 368820237922116,
					"parameters": {
						"layout": "\"Falso\""
					}
				}
			],
			"sid": 806624324307739
		},
		{
			"eventType": "block",
			"conditions": [
				{
					"id": "on-object-clicked",
					"objectClass": "Mouse",
					"sid": 244255112648126,
					"parameters": {
						"mouse-button": "left",
						"click-type": "clicked",
						"object-clicked": "C"
					}
				}
			],
			"actions": [
				{
					"id": "go-to-layout-by-name",
					"objectClass": "System",
					"sid": 234911525814186,
					"parameters": {
						"layout": "\"Verdadero\""
					}
				}
			],
			"sid": 254850107259294
		},
		{
			"eventType": "block",
			"conditions": [
				{
					"id": "on-object-clicked",
					"objectClass": "Mouse",
					"sid": 818134485737698,
					"parameters": {
						"mouse-button": "left",
						"click-type": "clicked",
						"object-clicked": "D"
					}
				}
			],
			"actions": [
				{
					"id": "go-to-layout-by-name",
					"objectClass": "System",
					"sid": 220647084885846,
					"parameters": {
						"layout": "\"Falso\""
					}
				}
			],
			"sid": 914344550008269
		}
	],
	"sid": 730767127604568
}