{
	"name": "pregunta 4",
	"events": [
		{
			"eventType": "block",
			"conditions": [
				{
					"id": "on-object-clicked",
					"objectClass": "Mouse",
					"sid": 882414495262859,
					"parameters": {
						"mouse-button": "left",
						"click-type": "clicked",
						"object-clicked": "A"
					}
				}
			],
			"actions": [
				{
					"id": "go-to-layout-by-name",
					"objectClass": "System",
					"sid": 758175266588490,
					"parameters": {
						"layout": "\"Falso\""
					}
				}
			],
			"sid": 880865762138147
		},
		{
			"eventType": "block",
			"conditions": [
				{
					"id": "on-object-clicked",
					"objectClass": "Mouse",
					"sid": 222684046916078,
					"parameters": {
						"mouse-button": "left",
						"click-type": "clicked",
						"object-clicked": "B"
					}
				}
			],
			"actions": [
				{
					"id": "go-to-layout-by-name",
					"objectClass": "System",
					"sid": 212995560653753,
					"parameters": {
						"layout": "\"Falso\""
					}
				}
			],
			"sid": 510438270058083
		},
		{
			"eventType": "block",
			"conditions": [
				{
					"id": "on-object-clicked",
					"objectClass": "Mouse",
					"sid": 183146135915436,
					"parameters": {
						"mouse-button": "left",
						"click-type": "clicked",
						"object-clicked": "C"
					}
				}
			],
			"actions": [
				{
					"id": "go-to-layout-by-name",
					"objectClass": "System",
					"sid": 392043679670680,
					"parameters": {
						"layout": "\"Falso\""
					}
				}
			],
			"sid": 764913682584492
		},
		{
			"eventType": "block",
			"conditions": [
				{
					"id": "on-object-clicked",
					"objectClass": "Mouse",
					"sid": 209532328179823,
					"parameters": {
						"mouse-button": "left",
						"click-type": "clicked",
						"object-clicked": "D"
					}
				}
			],
			"actions": [
				{
					"id": "go-to-layout-by-name",
					"objectClass": "System",
					"sid": 918657862815379,
					"parameters": {
						"layout": "\"Verdadero\""
					}
				}
			],
			"sid": 675108344283150
		}
	],
	"sid": 333892947216406
}